README.md
setup.py
nico_fib_py/__init__.py
nico_fib_py/version.py
nico_fib_py.egg-info/PKG-INFO
nico_fib_py.egg-info/SOURCES.txt
nico_fib_py.egg-info/dependency_links.txt
nico_fib_py.egg-info/entry_points.txt
nico_fib_py.egg-info/requires.txt
nico_fib_py.egg-info/top_level.txt
nico_fib_py/cmd/__init__.py
nico_fib_py/cmd/fib_number.py
nico_fib_py/fib_calcs/__init__.py
nico_fib_py/fib_calcs/fib_number.py
nico_fib_py/fib_calcs/fib_numbers.py
tests/__init__.py
tests/nico_fib_py/__init__.py
tests/nico_fib_py/fib_calcs/__init__.py
tests/nico_fib_py/fib_calcs/test_fib_number.py
tests/nico_fib_py/fib_calcs/test_fib_numbers.py