Metadata-Version: 2.1
Name: nico-fib-py
Version: 0.0.2
Summary: Calculates a Fibonacci number
Home-page: https://github.com/nicolask-perso/nico-fib.git
Author: NK
Author-email: nicolas.kateb@yahoo.fr
License: UNKNOWN
Platform: UNKNOWN
Classifier: Development Status :: 4 - Beta
Classifier: Programming Language :: Python :: 3
Classifier: Operating System :: OS Independent
Requires-Python: >=3
Provides-Extra: server
